elp_mpp02/__init__.py
elp_mpp02/mpp02.py
elp_mpp02-0.0.6.dist-info/licenses/LICENCE
elp_mpp02-0.0.6.dist-info/METADATA
elp_mpp02-0.0.6.dist-info/WHEEL
elp_mpp02-0.0.6.dist-info/top_level.txt
elp_mpp02-0.0.6.dist-info/RECORD
