Metadata-Version: 2.4
Name: elp_mpp02
Version: 0.0.6
Summary: Accurate Moon positions using the Lunar solution ELP/MPP02 in Python
Author-email: Marc van der Sluys <git@vandersluys.nl>
License-Expression: GPL-3.0-or-later
Project-URL: GitHub, https://github.com/MarcvdSluys/ELP-MPP02
Project-URL: ReadTheDocs, https://readthedocs.org/projects/elp-mpp02/
Keywords: Moon,astronomy,ephemeris
Classifier: Development Status :: 3 - Alpha
Classifier: Intended Audience :: Developers
Classifier: Intended Audience :: Education
Classifier: Intended Audience :: Science/Research
Classifier: Natural Language :: English
Classifier: Operating System :: OS Independent
Classifier: Programming Language :: Python :: 3
Classifier: Topic :: Scientific/Engineering :: Astronomy
License-File: LICENCE
Requires-Dist: numpy
Requires-Dist: fortranformat
Dynamic: license-file
